zerobuffer/__init__.py
zerobuffer/error_event_args.py
zerobuffer/exceptions.py
zerobuffer/oieb_view.py
zerobuffer/py.typed
zerobuffer/reader.py
zerobuffer/shared_memory.py
zerobuffer/types.py
zerobuffer/writer.py
zerobuffer/cross_platform/__init__.py
zerobuffer/cross_platform/__main__.py
zerobuffer/cross_platform/reader.py
zerobuffer/cross_platform/writer.py
zerobuffer/duplex/__init__.py
zerobuffer/duplex/client.py
zerobuffer/duplex/factory.py
zerobuffer/duplex/interfaces.py
zerobuffer/duplex/processing_mode.py
zerobuffer/duplex/server.py
zerobuffer/platform/__init__.py
zerobuffer/platform/base.py
zerobuffer/platform/darwin.py
zerobuffer/platform/linux.py
zerobuffer/platform/windows.py
zerobuffer_ipc-1.2.8.dist-info/licenses/LICENSE
zerobuffer_serve/__init__.py
zerobuffer_serve/__main__.py
zerobuffer_serve/async_manager.py
zerobuffer_serve/config.py
zerobuffer_serve/models.py
zerobuffer_serve/pydantic_integration_example.py
zerobuffer_serve/server.py
zerobuffer_serve/step_registry.py
zerobuffer_serve/test_context.py
zerobuffer_serve/test_data_patterns.py
zerobuffer_serve/logging/__init__.py
zerobuffer_serve/logging/dual_logger.py
zerobuffer_serve/logging/structured_logger.py
zerobuffer_serve/monitoring/resource_monitor.py
zerobuffer_serve/services/__init__.py
zerobuffer_serve/services/buffer_naming_service.py
zerobuffer_serve/step_definitions/__init__.py
zerobuffer_serve/step_definitions/base.py
zerobuffer_serve/step_definitions/basic_communication.py
zerobuffer_serve/step_definitions/basic_communication_refactored.py
zerobuffer_serve/step_definitions/benchmarks.py
zerobuffer_serve/step_definitions/duplex_channel.py
zerobuffer_serve/step_definitions/edge_cases.py
zerobuffer_serve/step_definitions/error_handling.py
zerobuffer_serve/step_definitions/initialization.py
zerobuffer_serve/step_definitions/performance.py
zerobuffer_serve/step_definitions/process_lifecycle.py
zerobuffer_serve/step_definitions/stress_tests.py
zerobuffer_serve/step_definitions/synchronization.py
zerobuffer_ipc-1.2.8.dist-info/METADATA
zerobuffer_ipc-1.2.8.dist-info/WHEEL
zerobuffer_ipc-1.2.8.dist-info/top_level.txt
zerobuffer_ipc-1.2.8.dist-info/RECORD
