Metadata-Version: 2.4
Name: zerobuffer-ipc
Version: 1.2.8
Summary: High-performance zero-copy inter-process communication library for video streaming
Home-page: https://github.com/zerobuffer/zerobuffer-python
Author: ZeroBuffer Contributors
Author-email: ModelingEvolution <info@modelingevolution.com>
License-Expression: MIT
Project-URL: Homepage, https://github.com/modelingevolution/zerobuffer
Project-URL: Documentation, https://github.com/modelingevolution/zerobuffer#readme
Project-URL: Repository, https://github.com/modelingevolution/zerobuffer
Project-URL: Issues, https://github.com/modelingevolution/zerobuffer/issues
Keywords: ipc,shared-memory,zero-copy,streaming,video
Classifier: Development Status :: 4 - Beta
Classifier: Intended Audience :: Developers
Classifier: Operating System :: OS Independent
Classifier: Programming Language :: Python :: 3
Classifier: Programming Language :: Python :: 3.8
Classifier: Programming Language :: Python :: 3.9
Classifier: Programming Language :: Python :: 3.10
Classifier: Programming Language :: Python :: 3.11
Classifier: Programming Language :: Python :: 3.12
Classifier: Topic :: System :: Hardware :: Symmetric Multi-processing
Classifier: Topic :: Software Development :: Libraries :: Python Modules
Requires-Python: >=3.8
License-File: LICENSE
Provides-Extra: linux
Requires-Dist: posix-ipc>=1.0.0; extra == "linux"
Provides-Extra: darwin
Requires-Dist: posix-ipc>=1.0.0; extra == "darwin"
Provides-Extra: windows
Requires-Dist: pywin32>=300; extra == "windows"
Provides-Extra: dev
Requires-Dist: pytest>=7.0; extra == "dev"
Requires-Dist: pytest-timeout>=2.0; extra == "dev"
Requires-Dist: pytest-cov>=4.0; extra == "dev"
Requires-Dist: pytest-benchmark>=4.0; extra == "dev"
Requires-Dist: black>=23.0; extra == "dev"
Requires-Dist: isort>=5.0; extra == "dev"
Requires-Dist: flake8>=6.0; extra == "dev"
Requires-Dist: mypy>=1.0; extra == "dev"
Requires-Dist: build>=0.10; extra == "dev"
Provides-Extra: docs
Requires-Dist: sphinx>=6.0; extra == "docs"
Requires-Dist: sphinx-rtd-theme>=1.0; extra == "docs"
Dynamic: author
Dynamic: home-page
Dynamic: license-file
Dynamic: requires-python
